README.md
setup.py
json_extract/__init__.py
json_extract.egg-info/PKG-INFO
json_extract.egg-info/SOURCES.txt
json_extract.egg-info/dependency_links.txt
json_extract.egg-info/top_level.txt