Metadata-Version: 2.1
Name: json-extract
Version: 1.1.0
Summary: json提取器
Home-page: https://github.com/TIM952597205/json_tool
Author: lsl
Author-email: 952597205@qq.com
License: UNKNOWN
Platform: UNKNOWN
Classifier: Programming Language :: Python :: 3
